{
    "uid": "9e7b553b-0adb-4426-968c-1319eee45c96",
    "name": "23_CatBoost_GoldenFeatures",
    "preprocessing": [
        {
            "golden_features": {
                "new_features": [
                    {
                        "feature1": "sun_addition",
                        "feature2": "location_a",
                        "operation": "multiply",
                        "score": 0.1978120638
                    },
                    {
                        "feature1": "sun_addition",
                        "feature2": "location_a",
                        "operation": "ratio",
                        "score": 0.1978120638
                    },
                    {
                        "feature1": "location_a",
                        "feature2": "sun_addition",
                        "operation": "ratio",
                        "score": 0.2231736186
                    },
                    {
                        "feature1": "direct_rad:W",
                        "feature2": "location_a",
                        "operation": "ratio",
                        "score": 0.2369044255
                    },
                    {
                        "feature1": "location_a",
                        "feature2": "direct_rad:W",
                        "operation": "multiply",
                        "score": 0.2369044255
                    },
                    {
                        "feature1": "sun_product",
                        "feature2": "location_a",
                        "operation": "ratio",
                        "score": 0.239947607
                    },
                    {
                        "feature1": "sun_product",
                        "feature2": "location_a",
                        "operation": "multiply",
                        "score": 0.239947607
                    },
                    {
                        "feature1": "direct_rad_1h:J",
                        "feature2": "location_a",
                        "operation": "ratio",
                        "score": 0.2504136075
                    },
                    {
                        "feature1": "location_a",
                        "feature2": "direct_rad_1h:J",
                        "operation": "multiply",
                        "score": 0.2504136075
                    },
                    {
                        "feature1": "location_a",
                        "feature2": "direct_rad:W",
                        "operation": "ratio",
                        "score": 0.2513528999
                    }
                ],
                "new_columns": [
                    "sun_addition_multiply_location_a",
                    "sun_addition_ratio_location_a",
                    "location_a_ratio_sun_addition",
                    "direct_rad:W_ratio_location_a",
                    "location_a_multiply_direct_rad:W",
                    "sun_product_ratio_location_a",
                    "sun_product_multiply_location_a",
                    "direct_rad_1h:J_ratio_location_a",
                    "location_a_multiply_direct_rad_1h:J",
                    "location_a_ratio_direct_rad:W"
                ],
                "ml_task": "regression"
            },
            "scale_y": {
                "scale": [
                    812.519618465985
                ],
                "mean": [
                    320.7768144317352
                ],
                "var": [
                    660188.1303921097
                ],
                "n_samples_seen": 61635,
                "n_features_in": 1,
                "columns": [
                    "target"
                ],
                "scale_method": "scale_normal"
            },
            "ml_task": "regression",
            "params": {
                "columns_preprocessing": {},
                "target_preprocessing": [
                    "na_exclude",
                    "scale_normal"
                ],
                "ml_task": "regression",
                "golden_features": {
                    "results_path": "automl",
                    "ml_task": "regression",
                    "n_jobs": -1
                }
            }
        },
        {
            "golden_features": {
                "new_features": [
                    {
                        "feature1": "sun_addition",
                        "feature2": "location_a",
                        "operation": "multiply",
                        "score": 0.1978120638
                    },
                    {
                        "feature1": "sun_addition",
                        "feature2": "location_a",
                        "operation": "ratio",
                        "score": 0.1978120638
                    },
                    {
                        "feature1": "location_a",
                        "feature2": "sun_addition",
                        "operation": "ratio",
                        "score": 0.2231736186
                    },
                    {
                        "feature1": "direct_rad:W",
                        "feature2": "location_a",
                        "operation": "ratio",
                        "score": 0.2369044255
                    },
                    {
                        "feature1": "location_a",
                        "feature2": "direct_rad:W",
                        "operation": "multiply",
                        "score": 0.2369044255
                    },
                    {
                        "feature1": "sun_product",
                        "feature2": "location_a",
                        "operation": "ratio",
                        "score": 0.239947607
                    },
                    {
                        "feature1": "sun_product",
                        "feature2": "location_a",
                        "operation": "multiply",
                        "score": 0.239947607
                    },
                    {
                        "feature1": "direct_rad_1h:J",
                        "feature2": "location_a",
                        "operation": "ratio",
                        "score": 0.2504136075
                    },
                    {
                        "feature1": "location_a",
                        "feature2": "direct_rad_1h:J",
                        "operation": "multiply",
                        "score": 0.2504136075
                    },
                    {
                        "feature1": "location_a",
                        "feature2": "direct_rad:W",
                        "operation": "ratio",
                        "score": 0.2513528999
                    }
                ],
                "new_columns": [
                    "sun_addition_multiply_location_a",
                    "sun_addition_ratio_location_a",
                    "location_a_ratio_sun_addition",
                    "direct_rad:W_ratio_location_a",
                    "location_a_multiply_direct_rad:W",
                    "sun_product_ratio_location_a",
                    "sun_product_multiply_location_a",
                    "direct_rad_1h:J_ratio_location_a",
                    "location_a_multiply_direct_rad_1h:J",
                    "location_a_ratio_direct_rad:W"
                ],
                "ml_task": "regression"
            },
            "scale_y": {
                "scale": [
                    809.7436346957782
                ],
                "mean": [
                    318.54968836699936
                ],
                "var": [
                    655684.7539303298
                ],
                "n_samples_seen": 61635,
                "n_features_in": 1,
                "columns": [
                    "target"
                ],
                "scale_method": "scale_normal"
            },
            "ml_task": "regression",
            "params": {
                "columns_preprocessing": {},
                "target_preprocessing": [
                    "na_exclude",
                    "scale_normal"
                ],
                "ml_task": "regression",
                "golden_features": {
                    "results_path": "automl",
                    "ml_task": "regression",
                    "n_jobs": -1
                }
            }
        },
        {
            "golden_features": {
                "new_features": [
                    {
                        "feature1": "sun_addition",
                        "feature2": "location_a",
                        "operation": "multiply",
                        "score": 0.1978120638
                    },
                    {
                        "feature1": "sun_addition",
                        "feature2": "location_a",
                        "operation": "ratio",
                        "score": 0.1978120638
                    },
                    {
                        "feature1": "location_a",
                        "feature2": "sun_addition",
                        "operation": "ratio",
                        "score": 0.2231736186
                    },
                    {
                        "feature1": "direct_rad:W",
                        "feature2": "location_a",
                        "operation": "ratio",
                        "score": 0.2369044255
                    },
                    {
                        "feature1": "location_a",
                        "feature2": "direct_rad:W",
                        "operation": "multiply",
                        "score": 0.2369044255
                    },
                    {
                        "feature1": "sun_product",
                        "feature2": "location_a",
                        "operation": "ratio",
                        "score": 0.239947607
                    },
                    {
                        "feature1": "sun_product",
                        "feature2": "location_a",
                        "operation": "multiply",
                        "score": 0.239947607
                    },
                    {
                        "feature1": "direct_rad_1h:J",
                        "feature2": "location_a",
                        "operation": "ratio",
                        "score": 0.2504136075
                    },
                    {
                        "feature1": "location_a",
                        "feature2": "direct_rad_1h:J",
                        "operation": "multiply",
                        "score": 0.2504136075
                    },
                    {
                        "feature1": "location_a",
                        "feature2": "direct_rad:W",
                        "operation": "ratio",
                        "score": 0.2513528999
                    }
                ],
                "new_columns": [
                    "sun_addition_multiply_location_a",
                    "sun_addition_ratio_location_a",
                    "location_a_ratio_sun_addition",
                    "direct_rad:W_ratio_location_a",
                    "location_a_multiply_direct_rad:W",
                    "sun_product_ratio_location_a",
                    "sun_product_multiply_location_a",
                    "direct_rad_1h:J_ratio_location_a",
                    "location_a_multiply_direct_rad_1h:J",
                    "location_a_ratio_direct_rad:W"
                ],
                "ml_task": "regression"
            },
            "scale_y": {
                "scale": [
                    798.557348353759
                ],
                "mean": [
                    313.6506203050215
                ],
                "var": [
                    637693.8386097868
                ],
                "n_samples_seen": 61635,
                "n_features_in": 1,
                "columns": [
                    "target"
                ],
                "scale_method": "scale_normal"
            },
            "ml_task": "regression",
            "params": {
                "columns_preprocessing": {},
                "target_preprocessing": [
                    "na_exclude",
                    "scale_normal"
                ],
                "ml_task": "regression",
                "golden_features": {
                    "results_path": "automl",
                    "ml_task": "regression",
                    "n_jobs": -1
                }
            }
        },
        {
            "golden_features": {
                "new_features": [
                    {
                        "feature1": "sun_addition",
                        "feature2": "location_a",
                        "operation": "multiply",
                        "score": 0.1978120638
                    },
                    {
                        "feature1": "sun_addition",
                        "feature2": "location_a",
                        "operation": "ratio",
                        "score": 0.1978120638
                    },
                    {
                        "feature1": "location_a",
                        "feature2": "sun_addition",
                        "operation": "ratio",
                        "score": 0.2231736186
                    },
                    {
                        "feature1": "direct_rad:W",
                        "feature2": "location_a",
                        "operation": "ratio",
                        "score": 0.2369044255
                    },
                    {
                        "feature1": "location_a",
                        "feature2": "direct_rad:W",
                        "operation": "multiply",
                        "score": 0.2369044255
                    },
                    {
                        "feature1": "sun_product",
                        "feature2": "location_a",
                        "operation": "ratio",
                        "score": 0.239947607
                    },
                    {
                        "feature1": "sun_product",
                        "feature2": "location_a",
                        "operation": "multiply",
                        "score": 0.239947607
                    },
                    {
                        "feature1": "direct_rad_1h:J",
                        "feature2": "location_a",
                        "operation": "ratio",
                        "score": 0.2504136075
                    },
                    {
                        "feature1": "location_a",
                        "feature2": "direct_rad_1h:J",
                        "operation": "multiply",
                        "score": 0.2504136075
                    },
                    {
                        "feature1": "location_a",
                        "feature2": "direct_rad:W",
                        "operation": "ratio",
                        "score": 0.2513528999
                    }
                ],
                "new_columns": [
                    "sun_addition_multiply_location_a",
                    "sun_addition_ratio_location_a",
                    "location_a_ratio_sun_addition",
                    "direct_rad:W_ratio_location_a",
                    "location_a_multiply_direct_rad:W",
                    "sun_product_ratio_location_a",
                    "sun_product_multiply_location_a",
                    "direct_rad_1h:J_ratio_location_a",
                    "location_a_multiply_direct_rad_1h:J",
                    "location_a_ratio_direct_rad:W"
                ],
                "ml_task": "regression"
            },
            "scale_y": {
                "scale": [
                    808.7677219310159
                ],
                "mean": [
                    317.0280977529002
                ],
                "var": [
                    654105.228037485
                ],
                "n_samples_seen": 61635,
                "n_features_in": 1,
                "columns": [
                    "target"
                ],
                "scale_method": "scale_normal"
            },
            "ml_task": "regression",
            "params": {
                "columns_preprocessing": {},
                "target_preprocessing": [
                    "na_exclude",
                    "scale_normal"
                ],
                "ml_task": "regression",
                "golden_features": {
                    "results_path": "automl",
                    "ml_task": "regression",
                    "n_jobs": -1
                }
            }
        },
        {
            "golden_features": {
                "new_features": [
                    {
                        "feature1": "sun_addition",
                        "feature2": "location_a",
                        "operation": "multiply",
                        "score": 0.1978120638
                    },
                    {
                        "feature1": "sun_addition",
                        "feature2": "location_a",
                        "operation": "ratio",
                        "score": 0.1978120638
                    },
                    {
                        "feature1": "location_a",
                        "feature2": "sun_addition",
                        "operation": "ratio",
                        "score": 0.2231736186
                    },
                    {
                        "feature1": "direct_rad:W",
                        "feature2": "location_a",
                        "operation": "ratio",
                        "score": 0.2369044255
                    },
                    {
                        "feature1": "location_a",
                        "feature2": "direct_rad:W",
                        "operation": "multiply",
                        "score": 0.2369044255
                    },
                    {
                        "feature1": "sun_product",
                        "feature2": "location_a",
                        "operation": "ratio",
                        "score": 0.239947607
                    },
                    {
                        "feature1": "sun_product",
                        "feature2": "location_a",
                        "operation": "multiply",
                        "score": 0.239947607
                    },
                    {
                        "feature1": "direct_rad_1h:J",
                        "feature2": "location_a",
                        "operation": "ratio",
                        "score": 0.2504136075
                    },
                    {
                        "feature1": "location_a",
                        "feature2": "direct_rad_1h:J",
                        "operation": "multiply",
                        "score": 0.2504136075
                    },
                    {
                        "feature1": "location_a",
                        "feature2": "direct_rad:W",
                        "operation": "ratio",
                        "score": 0.2513528999
                    }
                ],
                "new_columns": [
                    "sun_addition_multiply_location_a",
                    "sun_addition_ratio_location_a",
                    "location_a_ratio_sun_addition",
                    "direct_rad:W_ratio_location_a",
                    "location_a_multiply_direct_rad:W",
                    "sun_product_ratio_location_a",
                    "sun_product_multiply_location_a",
                    "direct_rad_1h:J_ratio_location_a",
                    "location_a_multiply_direct_rad_1h:J",
                    "location_a_ratio_direct_rad:W"
                ],
                "ml_task": "regression"
            },
            "scale_y": {
                "scale": [
                    811.1991029384758
                ],
                "mean": [
                    319.70390019631384
                ],
                "var": [
                    658043.9846081879
                ],
                "n_samples_seen": 61636,
                "n_features_in": 1,
                "columns": [
                    "target"
                ],
                "scale_method": "scale_normal"
            },
            "ml_task": "regression",
            "params": {
                "columns_preprocessing": {},
                "target_preprocessing": [
                    "na_exclude",
                    "scale_normal"
                ],
                "ml_task": "regression",
                "golden_features": {
                    "results_path": "automl",
                    "ml_task": "regression",
                    "n_jobs": -1
                }
            }
        }
    ],
    "learners": [
        {
            "library_version": "1.2.2",
            "algorithm_name": "CatBoost",
            "algorithm_short_name": "CatBoost",
            "uid": "a5e16d04-d2fb-466f-bf42-7368de0c80b5",
            "params": {
                "model_type": "CatBoost",
                "ml_task": "regression",
                "n_jobs": -1,
                "seed": 43,
                "learning_rate": 0.1,
                "depth": 7,
                "rsm": 0.8,
                "loss_function": "RMSE",
                "eval_metric": "MAE",
                "explain_level": 0
            },
            "name": "learner_fold_0",
            "best_ntree_limit": 4723
        },
        {
            "library_version": "1.2.2",
            "algorithm_name": "CatBoost",
            "algorithm_short_name": "CatBoost",
            "uid": "89ca28ba-146d-4d79-a934-6c49aec05cce",
            "params": {
                "model_type": "CatBoost",
                "ml_task": "regression",
                "n_jobs": -1,
                "seed": 43,
                "learning_rate": 0.1,
                "depth": 7,
                "rsm": 0.8,
                "loss_function": "RMSE",
                "eval_metric": "MAE",
                "explain_level": 0
            },
            "name": "learner_fold_1",
            "best_ntree_limit": 5149
        },
        {
            "library_version": "1.2.2",
            "algorithm_name": "CatBoost",
            "algorithm_short_name": "CatBoost",
            "uid": "5fffa3c9-2b1c-4d84-b0e8-cdfc2b81f3b8",
            "params": {
                "model_type": "CatBoost",
                "ml_task": "regression",
                "n_jobs": -1,
                "seed": 43,
                "learning_rate": 0.1,
                "depth": 7,
                "rsm": 0.8,
                "loss_function": "RMSE",
                "eval_metric": "MAE",
                "explain_level": 0
            },
            "name": "learner_fold_2",
            "best_ntree_limit": 6052
        },
        {
            "library_version": "1.2.2",
            "algorithm_name": "CatBoost",
            "algorithm_short_name": "CatBoost",
            "uid": "9068ab62-b086-4df6-88f5-f9d3907c9a10",
            "params": {
                "model_type": "CatBoost",
                "ml_task": "regression",
                "n_jobs": -1,
                "seed": 43,
                "learning_rate": 0.1,
                "depth": 7,
                "rsm": 0.8,
                "loss_function": "RMSE",
                "eval_metric": "MAE",
                "explain_level": 0
            },
            "name": "learner_fold_3",
            "best_ntree_limit": 6034
        },
        {
            "library_version": "1.2.2",
            "algorithm_name": "CatBoost",
            "algorithm_short_name": "CatBoost",
            "uid": "8a5691c3-b40a-4949-bfb7-ba212ed0de7c",
            "params": {
                "model_type": "CatBoost",
                "ml_task": "regression",
                "n_jobs": -1,
                "seed": 43,
                "learning_rate": 0.1,
                "depth": 7,
                "rsm": 0.8,
                "loss_function": "RMSE",
                "eval_metric": "MAE",
                "explain_level": 0
            },
            "name": "learner_fold_4",
            "best_ntree_limit": 5566
        }
    ],
    "params": {
        "additional": {
            "max_rounds": 10000,
            "early_stopping_rounds": 50,
            "max_rows_limit": null,
            "max_cols_limit": null
        },
        "preprocessing": {
            "columns_preprocessing": {},
            "target_preprocessing": [
                "na_exclude",
                "scale_normal"
            ],
            "ml_task": "regression",
            "golden_features": {
                "results_path": "automl",
                "ml_task": "regression",
                "n_jobs": -1
            }
        },
        "validation_strategy": {
            "validation_type": "kfold",
            "k_folds": 5,
            "shuffle": true,
            "random_seed": 42,
            "X_path": "automl/X.data",
            "y_path": "automl/y.data",
            "results_path": "automl"
        },
        "learner": {
            "model_type": "CatBoost",
            "ml_task": "regression",
            "n_jobs": -1,
            "seed": 43,
            "learning_rate": 0.1,
            "depth": 7,
            "rsm": 0.8,
            "loss_function": "RMSE",
            "eval_metric": "MAE",
            "explain_level": 0
        },
        "automl_random_state": 42,
        "ml_task": "regression",
        "explain_level": 0,
        "name": "23_CatBoost_GoldenFeatures",
        "status": "initialized",
        "final_loss": null,
        "train_time": null,
        "data_type": "original_golden_features",
        "max_time_for_learner": 60
    },
    "saved": [
        "23_CatBoost_GoldenFeatures/learner_fold_0.catboost",
        "23_CatBoost_GoldenFeatures/learner_fold_1.catboost",
        "23_CatBoost_GoldenFeatures/learner_fold_2.catboost",
        "23_CatBoost_GoldenFeatures/learner_fold_3.catboost",
        "23_CatBoost_GoldenFeatures/learner_fold_4.catboost"
    ],
    "predictions_fname": "23_CatBoost_GoldenFeatures/predictions_out_of_folds.csv",
    "metric_name": "mae",
    "final_loss": "78.23888114897778",
    "train_time": 252.13184309005737,
    "is_stacked": false,
    "joblib_version": "1.3.2"
}